LICENSE.md
README.md
pyproject.toml
setup.py
compaqt/__init__.py
compaqt/compaqt.c
compaqt/compaqt.pyi
compaqt.egg-info/PKG-INFO
compaqt.egg-info/SOURCES.txt
compaqt.egg-info/dependency_links.txt
compaqt.egg-info/top_level.txt
compaqt/globals/buftricks.h
compaqt/globals/exceptions.c
compaqt/globals/exceptions.h
compaqt/globals/internals.h
compaqt/globals/typedefs.h
compaqt/globals/typemasks.h
compaqt/main/regular.c
compaqt/main/regular.h
compaqt/main/serialization.c
compaqt/main/serialization.h
compaqt/main/stream.c
compaqt/main/stream.h
compaqt/main/validation.c
compaqt/main/validation.h
compaqt/settings/allocations.c
compaqt/settings/allocations.h
compaqt/types/base.h
compaqt/types/cbytes.c
compaqt/types/cbytes.h
compaqt/types/cstr.c
compaqt/types/cstr.h
compaqt/types/strdata.c
compaqt/types/strdata.h
compaqt/types/usertypes.c
compaqt/types/usertypes.h
tests/test_values.py