Metadata-Version: 2.1
Name: compaqt
Version: 1.1.0
Summary: A compact serializer aiming for flexibility and performance
Home-page: https://github.com/svenboertjens/compaqt
Author: Sven Boertjens
Author-email: boertjens.sven@gmail.com
License: BSD-3-Clause
Classifier: Programming Language :: Python :: 3
Classifier: Programming Language :: Python :: 3.7
Classifier: Programming Language :: Python :: 3.8
Classifier: Programming Language :: Python :: 3.9
Classifier: Programming Language :: Python :: 3.10
Classifier: Programming Language :: Python :: 3.11
Classifier: Programming Language :: Python :: 3.12
Classifier: Programming Language :: Python :: 3.13
Classifier: License :: OSI Approved :: BSD License
Classifier: Operating System :: OS Independent
Requires-Python: >=3.7, <=3.13
License-File: LICENSE.md
